minglight/__init__.py
minglight/mlight.py
minglight/tm.py
minglight-1.0.3.dist-info/METADATA
minglight-1.0.3.dist-info/RECORD
minglight-1.0.3.dist-info/WHEEL
minglight-1.0.3.dist-info/top_level.txt
